yta_temp/__init__.py
yta_temp-0.0.4.dist-info/licenses/LICENSE
yta_temp-0.0.4.dist-info/METADATA
yta_temp-0.0.4.dist-info/WHEEL
yta_temp-0.0.4.dist-info/RECORD
