Metadata-Version: 2.4
Name: yta-temp
Version: 0.0.4
Summary: Youtube Autonomous Temporary Module
License-File: LICENSE
Author: danialcala94
Author-email: danielalcalavalera@gmail.com
Requires-Python: ==3.9
Classifier: Programming Language :: Python :: 3
Classifier: Programming Language :: Python :: 3.9
Requires-Dist: yta_file (>=0.0.1,<1.0.0)
Requires-Dist: yta_programming (>=0.0.1,<1.0.0)
Requires-Dist: yta_programming_env (>=0.0.1,<1.0.0)
Requires-Dist: yta_programming_path (>=0.0.1,<1.0.0)
Requires-Dist: yta_random (>=0.0.1,<1.0.0)
Requires-Dist: yta_validation (>=0.0.1,<1.0.0)
